{
  "variables": {
    "iso_path": "",
    "iso_md5": ""
  },

  "builders": [
  {    
    "type": "vmware-iso",
    "communicator": "winrm",
    "disk_size": 61440,
    "floppy_files": [
      "Autounattend.xml",
      "update-windows.ps1",
      "configure-winrm.ps1"
    ],
    "guest_os_type": "windows9-64",
    "headless": true,
    "iso_url": "{{user `iso_path`}}",
    "iso_checksum_type": "md5",
    "iso_checksum": "{{user `iso_md5`}}",    
    "winrm_username": "vagrant",
    "winrm_password": "vagrant",
    "winrm_timeout": "6h",
    "shutdown_command": "shutdown /s /t 10 /f /d p:4:1 /c \"Packer Shutdown\"",
    "skip_compaction": false,
    "tools_upload_flavor": "windows",
    "tools_upload_path": "c:/Windows/Temp/windows.iso",
    "vmx_data": {
      "gui.fitguestusingnativedisplayresolution": "FALSE",
      "memsize": "1024",
      "numvcpus": "2",
      "virtualHW.version": "10",
      "scsi0.virtualDev": "lsisas1068"
      }
    },
  {    
    "type": "virtualbox-iso",
    "communicator": "winrm",
    "disk_size": 61440,
    "floppy_files": [
      "Autounattend.xml",
      "update-windows.ps1",
      "configure-winrm.ps1"
    ],
    "guest_os_type": "Windows10_64",
    "headless": true,
    "iso_url": "{{user `iso_path`}}",
    "iso_checksum_type": "md5",
    "iso_checksum": "{{user `iso_md5`}}",    
     "winrm_username": "vagrant",
    "winrm_password": "vagrant",
    "winrm_timeout": "6h",
    "shutdown_command": "shutdown /s /t 10 /f /d p:4:1 /c \"Packer Shutdown\"",
    "guest_additions_mode": "upload",
    "guest_additions_path": "c:/Windows/Temp/windows.iso",
    "vboxmanage": [
        [
          "modifyvm",
          "{{.Name}}",
          "--memory",
          "1024"
        ],
        [
          "modifyvm",
          "{{.Name}}",
          "--cpus",
          "2"
        ],
	[
	  "modifyvm",
	  "{{.Name}}",
	  "--vram", 
	  "32"
	]	
      ]
    } 
  ],
  "provisioners": [
  {
    "type": "powershell",
    "execute_command": "powershell -ExecutionPolicy Bypass \"& { {{.Vars}}{{.Path}}; exit $LastExitCode}\"",
    "scripts": [
      "install-guest-tools.ps1",
      "enable-rdp.ps1",
      "disable-hibernate.ps1",
      "disable-autologin.ps1",
      "enable-uac.ps1"
    ]},
  {
    "type": "windows-restart",
    "restart_command": "powershell \"& {(Get-WmiObject win32_operatingsystem).LastBootUpTime > C:\\ProgramData\\lastboot.txt; Restart-Computer -force}\"",
    "restart_check_command": "powershell -command \"& {if ((get-content C:\\ProgramData\\lastboot.txt) -eq (Get-WmiObject win32_operatingsystem).LastBootUpTime) {Write-Output 'Sleeping for 600 seconds to wait for reboot'; start-sleep 600} else {Write-Output 'Reboot complete'}}\""
  }

],  

 "post-processors": [
    {
      "type": "vagrant",
      "keep_input_artifact": false,
      "output": "{{.Provider}}_windows-10.box",
      "vagrantfile_template": "vagrantfile.template"
    }
  ]
}

